pyzlib/__init__.py
pyzlib/test/__init__.py
pyzlib/test/deflate.py
pyzlib/test/inflate.py
pyzlib/test/test.py
pyzlib-0.1.16.dist-info/LICENSE
pyzlib-0.1.16.dist-info/METADATA
pyzlib-0.1.16.dist-info/WHEEL
pyzlib-0.1.16.dist-info/top_level.txt
pyzlib-0.1.16.dist-info/RECORD
